BotAmino/BotAmino.py
BotAmino/__init__.py
BotAmino/aminofix/__init__.py
BotAmino/aminofix/acm.py
BotAmino/aminofix/client.py
BotAmino/aminofix/socket.py
BotAmino/aminofix/sub_client.py
BotAmino/aminofix/asyncfix/__init__.py
BotAmino/aminofix/asyncfix/acm.py
BotAmino/aminofix/asyncfix/client.py
BotAmino/aminofix/asyncfix/socket.py
BotAmino/aminofix/asyncfix/sub_client.py
BotAmino/aminofix/lib/__init__.py
BotAmino/aminofix/lib/util/__init__.py
BotAmino/aminofix/lib/util/exceptions.py
BotAmino/aminofix/lib/util/headers.py
BotAmino/aminofix/lib/util/helpers.py
BotAmino/aminofix/lib/util/objects.py
BotAmino-1.28.1.dist-info/LICENSE
BotAmino-1.28.1.dist-info/METADATA
BotAmino-1.28.1.dist-info/WHEEL
BotAmino-1.28.1.dist-info/top_level.txt
BotAmino-1.28.1.dist-info/RECORD
