Metadata-Version: 2.1
Name: BotAmino
Version: 1.28.1
Summary: A library to create Amino bots.
Home-page: https://github.com/ThePhoenix78/AminoBot
Download-URL: https://github.com/ThePhoenix78/AminoBot/tarball/master
Author: ThePhoenix78, Vedansh
Author-email: thephoenix788@gmail.com
License: MIT
Keywords: aminoapps,amino-py,amino,amino-bot,narvii,api,python,python3,python3.x,ThePhoenix78,AminoBot,BotAmino,botamino,aminobot
Classifier: Programming Language :: Python :: 3
Classifier: License :: OSI Approved :: MIT License
Classifier: Operating System :: OS Independent
License-File: LICENSE
Requires-Dist: requests
Requires-Dist: websocket-client
Requires-Dist: pathlib
